quri_parts/NOTICE
quri_parts/_quri_parts_meta.py
quri_parts-17.0.0.dist-info/LICENSE
quri_parts-17.0.0.dist-info/METADATA
quri_parts-17.0.0.dist-info/WHEEL
quri_parts-17.0.0.dist-info/RECORD
