Metadata-Version: 2.1
Name: quri-parts
Version: 17.0.0
Summary: Platform-independent quantum computing library
Home-page: https://github.com/QunaSys/quri-parts
License: Apache-2.0
Keywords: quantum,quantum computing
Author: QURI Parts Authors
Author-email: opensource@qunasys.com
Requires-Python: >=3.9.8,<3.12
Classifier: License :: OSI Approved :: Apache Software License
Classifier: Programming Language :: Python :: 3
Classifier: Programming Language :: Python :: 3.10
Classifier: Programming Language :: Python :: 3.11
Classifier: Topic :: Scientific/Engineering :: Physics
Classifier: Typing :: Typed
Provides-Extra: braket
Provides-Extra: cirq
Provides-Extra: ionq
Provides-Extra: itensor
Provides-Extra: openfermion
Provides-Extra: openqasm
Provides-Extra: pyscf
Provides-Extra: qiskit
Provides-Extra: quantinuum
Provides-Extra: qulacs
Provides-Extra: stim
Provides-Extra: tket
Requires-Dist: quri-parts-algo
Requires-Dist: quri-parts-braket ; extra == "braket"
Requires-Dist: quri-parts-chem
Requires-Dist: quri-parts-circuit
Requires-Dist: quri-parts-cirq ; extra == "cirq"
Requires-Dist: quri-parts-core
Requires-Dist: quri-parts-ionq ; extra == "ionq"
Requires-Dist: quri-parts-itensor ; extra == "itensor"
Requires-Dist: quri-parts-openfermion ; extra == "openfermion"
Requires-Dist: quri-parts-openqasm ; extra == "openqasm"
Requires-Dist: quri-parts-pyscf ; extra == "pyscf"
Requires-Dist: quri-parts-qiskit ; extra == "qiskit"
Requires-Dist: quri-parts-quantinuum ; extra == "quantinuum"
Requires-Dist: quri-parts-qulacs ; extra == "qulacs"
Requires-Dist: quri-parts-stim ; extra == "stim"
Requires-Dist: quri-parts-tket ; extra == "tket"
Project-URL: Documentation, https://quri-parts.qunasys.com
Project-URL: Repository, https://github.com/QunaSys/quri-parts
